odoo/addons/mrp_auto_assign/README.rst
odoo/addons/mrp_auto_assign/__init__.py
odoo/addons/mrp_auto_assign/__manifest__.py
odoo/addons/mrp_auto_assign/i18n/de.po
odoo/addons/mrp_auto_assign/i18n/es.po
odoo/addons/mrp_auto_assign/i18n/es_MX.po
odoo/addons/mrp_auto_assign/i18n/fr.po
odoo/addons/mrp_auto_assign/i18n/gl.po
odoo/addons/mrp_auto_assign/i18n/hr.po
odoo/addons/mrp_auto_assign/i18n/hr_HR.po
odoo/addons/mrp_auto_assign/i18n/it.po
odoo/addons/mrp_auto_assign/i18n/lt.po
odoo/addons/mrp_auto_assign/i18n/mrp_auto_assign.pot
odoo/addons/mrp_auto_assign/i18n/nl_NL.po
odoo/addons/mrp_auto_assign/i18n/pt_BR.po
odoo/addons/mrp_auto_assign/i18n/ro.po
odoo/addons/mrp_auto_assign/i18n/sl.po
odoo/addons/mrp_auto_assign/i18n/tr.po
odoo/addons/mrp_auto_assign/i18n/vi_VN.po
odoo/addons/mrp_auto_assign/i18n/zh_CN.po
odoo/addons/mrp_auto_assign/models/__init__.py
odoo/addons/mrp_auto_assign/models/mrp_production.py
odoo/addons/mrp_auto_assign/readme/CONTRIBUTORS.rst
odoo/addons/mrp_auto_assign/readme/DESCRIPTION.rst
odoo/addons/mrp_auto_assign/readme/ROADMAP.rst
odoo/addons/mrp_auto_assign/readme/USAGE.rst
odoo/addons/mrp_auto_assign/static/description/icon.png
odoo/addons/mrp_auto_assign/static/description/index.html
odoo/addons/mrp_auto_assign/tests/__init__.py
odoo/addons/mrp_auto_assign/tests/test_auto_assign.py
odoo14_addon_mrp_auto_assign-14.0.1.0.1.dev3.dist-info/METADATA
odoo14_addon_mrp_auto_assign-14.0.1.0.1.dev3.dist-info/WHEEL
odoo14_addon_mrp_auto_assign-14.0.1.0.1.dev3.dist-info/top_level.txt
odoo14_addon_mrp_auto_assign-14.0.1.0.1.dev3.dist-info/RECORD
